noo/__init__.py
noo/__main__.py
noo/cli/__init__.py
noo/cli/components/__init__.py
noo/cli/components/config.py
noo/cli/components/registry.py
noo/impl/__init__.py
noo/impl/core/__init__.py
noo/impl/core/core.py
noo/impl/core/formatter.py
noo/impl/core/runner.py
noo/impl/core/variables.py
noo/impl/models/__init__.py
noo/impl/models/actions.py
noo/impl/models/noofile.py
noo/impl/packager/__init__.py
noo/impl/packager/packager.py
noo/impl/packager/reader.py
noo/impl/packager/runners/__init__.py
noo/impl/packager/runners/base.py
noo/impl/packager/runners/javascript.py
noo/impl/packager/runners/python_poetry.py
noo/impl/registry/__init__.py
noo/impl/registry/index.py
noo/impl/registry/local.py
noo/impl/registry/registry.py
noo/impl/registry/remote.py
noo/impl/resolvers/__init__.py
noo/impl/resolvers/github.py
noo/impl/resolvers/local.py
noo/impl/utils/__init__.py
noo/impl/utils/echo.py
noo/impl/utils/errors.py
noo/impl/utils/store.py
noo-2.0.0rc1.dist-info/entry_points.txt
noo-2.0.0rc1.dist-info/LICENSE
noo-2.0.0rc1.dist-info/WHEEL
noo-2.0.0rc1.dist-info/METADATA
noo-2.0.0rc1.dist-info/RECORD
